[{"iss_position": {"latitude": "51.1407", "longitude": "-27.1154"}, "message": "success", "timestamp": 1628016602}, {"iss_position": {"latitude": "51.1360", "longitude": "-27.0665"}, "message": "success", "timestamp": 1628016603}, {"iss_position": {"latitude": "51.1313", "longitude": "-27.0175"}, "message": "success", "timestamp": 1628016603}, {"iss_position": {"latitude": "51.1265", "longitude": "-26.9685"}, "message": "success", "timestamp": 1628016604}, {"iss_position": {"latitude": "51.1218", "longitude": "-26.9196"}, "message": "success", "timestamp": 1628016604}, {"iss_position": {"latitude": "51.1218", "longitude": "-26.9196"}, "message": "success", "timestamp": 1628016604}, {"iss_position": {"latitude": "51.1170", "longitude": "-26.8707"}, "message": "success", "timestamp": 1628016605}, {"iss_position": {"latitude": "51.1122", "longitude": "-26.8218"}, "message": "success", "timestamp": 1628016605}, {"iss_position": {"latitude": "51.1074", "longitude": "-26.7729"}, "message": "success", "timestamp": 1628016606}, {"iss_position": {"latitude": "51.1025", "longitude": "-26.7240"}, "message": "success", "timestamp": 1628016606}, {"iss_position": {"latitude": "51.1025", "longitude": "-26.7240"}, "message": "success", "timestamp": 1628016606}, {"iss_position": {"latitude": "51.0977", "longitude": "-26.6751"}, "message": "success", "timestamp": 1628016607}, {"iss_position": {"latitude": "51.0928", "longitude": "-26.6263"}, "message": "success", "timestamp": 1628016607}, {"iss_position": {"latitude": "51.0879", "longitude": "-26.5774"}, "message": "success", "timestamp": 1628016608}, {"iss_position": {"latitude": "51.0829", "longitude": "-26.5286"}, "message": "success", "timestamp": 1628016608}, {"iss_position": {"latitude": "51.0780", "longitude": "-26.4798"}, "message": "success", "timestamp": 1628016609}, {"iss_position": {"latitude": "51.0730", "longitude": "-26.4310"}, "message": "success", "timestamp": 1628016609}, {"iss_position": {"latitude": "51.0730", "longitude": "-26.4310"}, "message": "success", "timestamp": 1628016609}, {"iss_position": {"latitude": "51.0680", "longitude": "-26.3822"}, "message": "success", "timestamp": 1628016610}, {"iss_position": {"latitude": "51.0630", "longitude": "-26.3334"}, "message": "success", "timestamp": 1628016610}, {"iss_position": {"latitude": "51.0579", "longitude": "-26.2846"}, "message": "success", "timestamp": 1628016611}, {"iss_position": {"latitude": "51.0529", "longitude": "-26.2358"}, "message": "success", "timestamp": 1628016611}, {"iss_position": {"latitude": "51.0478", "longitude": "-26.1871"}, "message": "success", "timestamp": 1628016612}, {"iss_position": {"latitude": "51.0427", "longitude": "-26.1383"}, "message": "success", "timestamp": 1628016612}, {"iss_position": {"latitude": "51.0427", "longitude": "-26.1383"}, "message": "success", "timestamp": 1628016612}, {"iss_position": {"latitude": "51.0375", "longitude": "-26.0895"}, "message": "success", "timestamp": 1628016613}, {"iss_position": {"latitude": "51.0324", "longitude": "-26.0408"}, "message": "success", "timestamp": 1628016613}, {"iss_position": {"latitude": "51.0272", "longitude": "-25.9921"}, "message": "success", "timestamp": 1628016614}, {"iss_position": {"latitude": "51.0220", "longitude": "-25.9432"}, "message": "success", "timestamp": 1628016614}, {"iss_position": {"latitude": "51.0167", "longitude": "-25.8945"}, "message": "success", "timestamp": 1628016615}, {"iss_position": {"latitude": "51.0167", "longitude": "-25.8945"}, "message": "success", "timestamp": 1628016615}, {"iss_position": {"latitude": "51.0115", "longitude": "-25.8459"}, "message": "success", "timestamp": 1628016615}, {"iss_position": {"latitude": "51.0062", "longitude": "-25.7972"}, "message": "success", "timestamp": 1628016616}, {"iss_position": {"latitude": "51.0009", "longitude": "-25.7485"}, "message": "success", "timestamp": 1628016616}, {"iss_position": {"latitude": "50.9956", "longitude": "-25.6998"}, "message": "success", "timestamp": 1628016617}, {"iss_position": {"latitude": "50.9903", "longitude": "-25.6512"}, "message": "success", "timestamp": 1628016617}, {"iss_position": {"latitude": "50.9849", "longitude": "-25.6026"}, "message": "success", "timestamp": 1628016618}, {"iss_position": {"latitude": "50.9849", "longitude": "-25.6026"}, "message": "success", "timestamp": 1628016618}, {"iss_position": {"latitude": "50.9796", "longitude": "-25.5539"}, "message": "success", "timestamp": 1628016618}, {"iss_position": {"latitude": "50.9742", "longitude": "-25.5053"}, "message": "success", "timestamp": 1628016619}, {"iss_position": {"latitude": "50.9687", "longitude": "-25.4567"}, "message": "success", "timestamp": 1628016619}, {"iss_position": {"latitude": "50.9633", "longitude": "-25.4081"}, "message": "success", "timestamp": 1628016620}, {"iss_position": {"latitude": "50.9578", "longitude": "-25.3595"}, "message": "success", "timestamp": 1628016620}, {"iss_position": {"latitude": "50.9523", "longitude": "-25.3109"}, "message": "success", "timestamp": 1628016621}, {"iss_position": {"latitude": "50.9523", "longitude": "-25.3109"}, "message": "success", "timestamp": 1628016621}, {"iss_position": {"latitude": "50.9468", "longitude": "-25.2624"}, "message": "success", "timestamp": 1628016621}, {"iss_position": {"latitude": "50.9413", "longitude": "-25.2139"}, "message": "success", "timestamp": 1628016622}, {"iss_position": {"latitude": "50.9357", "longitude": "-25.1653"}, "message": "success", "timestamp": 1628016622}, {"iss_position": {"latitude": "50.9302", "longitude": "-25.1168"}, "message": "success", "timestamp": 1628016623}, {"iss_position": {"latitude": "50.9246", "longitude": "-25.0684"}, "message": "success", "timestamp": 1628016623}, {"iss_position": {"latitude": "50.9246", "longitude": "-25.0684"}, "message": "success", "timestamp": 1628016623}, {"iss_position": {"latitude": "50.9190", "longitude": "-25.0199"}, "message": "success", "timestamp": 1628016624}, {"iss_position": {"latitude": "50.9133", "longitude": "-24.9714"}, "message": "success", "timestamp": 1628016624}, {"iss_position": {"latitude": "50.9077", "longitude": "-24.9229"}, "message": "success", "timestamp": 1628016625}, {"iss_position": {"latitude": "50.9020", "longitude": "-24.8745"}, "message": "success", "timestamp": 1628016625}, {"iss_position": {"latitude": "50.8963", "longitude": "-24.8261"}, "message": "success", "timestamp": 1628016626}, {"iss_position": {"latitude": "50.8963", "longitude": "-24.8261"}, "message": "success", "timestamp": 1628016626}, {"iss_position": {"latitude": "50.8905", "longitude": "-24.7776"}, "message": "success", "timestamp": 1628016626}, {"iss_position": {"latitude": "50.8848", "longitude": "-24.7292"}, "message": "success", "timestamp": 1628016627}, {"iss_position": {"latitude": "50.8790", "longitude": "-24.6808"}, "message": "success", "timestamp": 1628016627}, {"iss_position": {"latitude": "50.8732", "longitude": "-24.6325"}, "message": "success", "timestamp": 1628016628}, {"iss_position": {"latitude": "50.8674", "longitude": "-24.5841"}, "message": "success", "timestamp": 1628016628}, {"iss_position": {"latitude": "50.8616", "longitude": "-24.5357"}, "message": "success", "timestamp": 1628016629}, {"iss_position": {"latitude": "50.8616", "longitude": "-24.5357"}, "message": "success", "timestamp": 1628016629}, {"iss_position": {"latitude": "50.8557", "longitude": "-24.4874"}, "message": "success", "timestamp": 1628016630}, {"iss_position": {"latitude": "50.8499", "longitude": "-24.4391"}, "message": "success", "timestamp": 1628016630}, {"iss_position": {"latitude": "50.8440", "longitude": "-24.3908"}, "message": "success", "timestamp": 1628016631}, {"iss_position": {"latitude": "50.8380", "longitude": "-24.3424"}, "message": "success", "timestamp": 1628016631}, {"iss_position": {"latitude": "50.8321", "longitude": "-24.2941"}, "message": "success", "timestamp": 1628016632}, {"iss_position": {"latitude": "50.8321", "longitude": "-24.2941"}, "message": "success", "timestamp": 1628016632}, {"iss_position": {"latitude": "50.8261", "longitude": "-24.2458"}, "message": "success", "timestamp": 1628016632}, {"iss_position": {"latitude": "50.8201", "longitude": "-24.1976"}, "message": "success", "timestamp": 1628016633}, {"iss_position": {"latitude": "50.8141", "longitude": "-24.1493"}, "message": "success", "timestamp": 1628016633}, {"iss_position": {"latitude": "50.8081", "longitude": "-24.1010"}, "message": "success", "timestamp": 1628016634}, {"iss_position": {"latitude": "50.8020", "longitude": "-24.0528"}, "message": "success", "timestamp": 1628016634}, {"iss_position": {"latitude": "50.7960", "longitude": "-24.0046"}, "message": "success", "timestamp": 1628016635}, {"iss_position": {"latitude": "50.7960", "longitude": "-24.0046"}, "message": "success", "timestamp": 1628016635}, {"iss_position": {"latitude": "50.7899", "longitude": "-23.9564"}, "message": "success", "timestamp": 1628016635}, {"iss_position": {"latitude": "50.7837", "longitude": "-23.9082"}, "message": "success", "timestamp": 1628016636}, {"iss_position": {"latitude": "50.7776", "longitude": "-23.8600"}, "message": "success", "timestamp": 1628016636}, {"iss_position": {"latitude": "50.7714", "longitude": "-23.8118"}, "message": "success", "timestamp": 1628016637}, {"iss_position": {"latitude": "50.7653", "longitude": "-23.7637"}, "message": "success", "timestamp": 1628016637}, {"iss_position": {"latitude": "50.7591", "longitude": "-23.7156"}, "message": "success", "timestamp": 1628016638}, {"iss_position": {"latitude": "50.7591", "longitude": "-23.7156"}, "message": "success", "timestamp": 1628016638}, {"iss_position": {"latitude": "50.7528", "longitude": "-23.6674"}, "message": "success", "timestamp": 1628016638}, {"iss_position": {"latitude": "50.7466", "longitude": "-23.6193"}, "message": "success", "timestamp": 1628016639}, {"iss_position": {"latitude": "50.7403", "longitude": "-23.5712"}, "message": "success", "timestamp": 1628016639}, {"iss_position": {"latitude": "50.7340", "longitude": "-23.5232"}, "message": "success", "timestamp": 1628016640}, {"iss_position": {"latitude": "50.7277", "longitude": "-23.4751"}, "message": "success", "timestamp": 1628016640}, {"iss_position": {"latitude": "50.7214", "longitude": "-23.4270"}, "message": "success", "timestamp": 1628016641}, {"iss_position": {"latitude": "50.7214", "longitude": "-23.4270"}, "message": "success", "timestamp": 1628016641}, {"iss_position": {"latitude": "50.7150", "longitude": "-23.3790"}, "message": "success", "timestamp": 1628016641}, {"iss_position": {"latitude": "50.7086", "longitude": "-23.3309"}, "message": "success", "timestamp": 1628016642}, {"iss_position": {"latitude": "50.7022", "longitude": "-23.2829"}, "message": "success", "timestamp": 1628016642}, {"iss_position": {"latitude": "50.6958", "longitude": "-23.2349"}, "message": "success", "timestamp": 1628016643}, {"iss_position": {"latitude": "50.6894", "longitude": "-23.1869"}, "message": "success", "timestamp": 1628016643}, {"iss_position": {"latitude": "50.6829", "longitude": "-23.1390"}, "message": "success", "timestamp": 1628016644}, {"iss_position": {"latitude": "50.6829", "longitude": "-23.1390"}, "message": "success", "timestamp": 1628016644}, {"iss_position": {"latitude": "50.6764", "longitude": "-23.0910"}, "message": "success", "timestamp": 1628016644}, {"iss_position": {"latitude": "50.6699", "longitude": "-23.0431"}, "message": "success", "timestamp": 1628016645}, {"iss_position": {"latitude": "50.6634", "longitude": "-22.9951"}, "message": "success", "timestamp": 1628016645}, {"iss_position": {"latitude": "50.6569", "longitude": "-22.9472"}, "message": "success", "timestamp": 1628016646}, {"iss_position": {"latitude": "50.6503", "longitude": "-22.8993"}, "message": "success", "timestamp": 1628016646}, {"iss_position": {"latitude": "50.6437", "longitude": "-22.8514"}, "message": "success", "timestamp": 1628016647}, {"iss_position": {"latitude": "50.6371", "longitude": "-22.8035"}, "message": "success", "timestamp": 1628016647}, {"iss_position": {"latitude": "50.6371", "longitude": "-22.8035"}, "message": "success", "timestamp": 1628016647}, {"iss_position": {"latitude": "50.6304", "longitude": "-22.7556"}, "message": "success", "timestamp": 1628016648}, {"iss_position": {"latitude": "50.6238", "longitude": "-22.7078"}, "message": "success", "timestamp": 1628016648}, {"iss_position": {"latitude": "50.6171", "longitude": "-22.6600"}, "message": "success", "timestamp": 1628016649}, {"iss_position": {"latitude": "50.6104", "longitude": "-22.6121"}, "message": "success", "timestamp": 1628016649}, {"iss_position": {"latitude": "50.6037", "longitude": "-22.5643"}, "message": "success", "timestamp": 1628016650}, {"iss_position": {"latitude": "50.5969", "longitude": "-22.5165"}, "message": "success", "timestamp": 1628016650}, {"iss_position": {"latitude": "50.5969", "longitude": "-22.5165"}, "message": "success", "timestamp": 1628016650}, {"iss_position": {"latitude": "50.5902", "longitude": "-22.4688"}, "message": "success", "timestamp": 1628016651}, {"iss_position": {"latitude": "50.5834", "longitude": "-22.4210"}, "message": "success", "timestamp": 1628016651}, {"iss_position": {"latitude": "50.5766", "longitude": "-22.3733"}, "message": "success", "timestamp": 1628016652}, {"iss_position": {"latitude": "50.5698", "longitude": "-22.3255"}, "message": "success", "timestamp": 1628016652}, {"iss_position": {"latitude": "50.5629", "longitude": "-22.2778"}, "message": "success", "timestamp": 1628016653}, {"iss_position": {"latitude": "50.5561", "longitude": "-22.2301"}, "message": "success", "timestamp": 1628016653}, {"iss_position": {"latitude": "50.5492", "longitude": "-22.1824"}, "message": "success", "timestamp": 1628016654}, {"iss_position": {"latitude": "50.5423", "longitude": "-22.1348"}, "message": "success", "timestamp": 1628016654}, {"iss_position": {"latitude": "50.5353", "longitude": "-22.0871"}, "message": "success", "timestamp": 1628016655}, {"iss_position": {"latitude": "50.5353", "longitude": "-22.0871"}, "message": "success", "timestamp": 1628016655}, {"iss_position": {"latitude": "50.5284", "longitude": "-22.0395"}, "message": "success", "timestamp": 1628016655}, {"iss_position": {"latitude": "50.5214", "longitude": "-21.9918"}, "message": "success", "timestamp": 1628016656}, {"iss_position": {"latitude": "50.5144", "longitude": "-21.9442"}, "message": "success", "timestamp": 1628016656}, {"iss_position": {"latitude": "50.5074", "longitude": "-21.8966"}, "message": "success", "timestamp": 1628016657}, {"iss_position": {"latitude": "50.5003", "longitude": "-21.8490"}, "message": "success", "timestamp": 1628016657}, {"iss_position": {"latitude": "50.4933", "longitude": "-21.8014"}, "message": "success", "timestamp": 1628016658}, {"iss_position": {"latitude": "50.4862", "longitude": "-21.7538"}, "message": "success", "timestamp": 1628016658}, {"iss_position": {"latitude": "50.4791", "longitude": "-21.7062"}, "message": "success", "timestamp": 1628016659}, {"iss_position": {"latitude": "50.4791", "longitude": "-21.7062"}, "message": "success", "timestamp": 1628016659}, {"iss_position": {"latitude": "50.4720", "longitude": "-21.6587"}, "message": "success", "timestamp": 1628016659}, {"iss_position": {"latitude": "50.4648", "longitude": "-21.6112"}, "message": "success", "timestamp": 1628016660}, {"iss_position": {"latitude": "50.4577", "longitude": "-21.5637"}, "message": "success", "timestamp": 1628016660}, {"iss_position": {"latitude": "50.4505", "longitude": "-21.5162"}, "message": "success", "timestamp": 1628016661}, {"iss_position": {"latitude": "50.4433", "longitude": "-21.4687"}, "message": "success", "timestamp": 1628016661}, {"iss_position": {"latitude": "50.4360", "longitude": "-21.4213"}, "message": "success", "timestamp": 1628016662}, {"iss_position": {"latitude": "50.4360", "longitude": "-21.4213"}, "message": "success", "timestamp": 1628016662}, {"iss_position": {"latitude": "50.4288", "longitude": "-21.3738"}, "message": "success", "timestamp": 1628016662}, {"iss_position": {"latitude": "50.4215", "longitude": "-21.3264"}, "message": "success", "timestamp": 1628016663}, {"iss_position": {"latitude": "50.4142", "longitude": "-21.2790"}, "message": "success", "timestamp": 1628016663}, {"iss_position": {"latitude": "50.4069", "longitude": "-21.2316"}, "message": "success", "timestamp": 1628016664}, {"iss_position": {"latitude": "50.3996", "longitude": "-21.1843"}, "message": "success", "timestamp": 1628016664}, {"iss_position": {"latitude": "50.3922", "longitude": "-21.1369"}, "message": "success", "timestamp": 1628016665}, {"iss_position": {"latitude": "50.3922", "longitude": "-21.1369"}, "message": "success", "timestamp": 1628016665}, {"iss_position": {"latitude": "50.3849", "longitude": "-21.0896"}, "message": "success", "timestamp": 1628016665}, {"iss_position": {"latitude": "50.3775", "longitude": "-21.0423"}, "message": "success", "timestamp": 1628016666}, {"iss_position": {"latitude": "50.3700", "longitude": "-20.9949"}, "message": "success", "timestamp": 1628016666}, {"iss_position": {"latitude": "50.3626", "longitude": "-20.9477"}, "message": "success", "timestamp": 1628016667}, {"iss_position": {"latitude": "50.3551", "longitude": "-20.9004"}, "message": "success", "timestamp": 1628016667}, {"iss_position": {"latitude": "50.3477", "longitude": "-20.8531"}, "message": "success", "timestamp": 1628016668}, {"iss_position": {"latitude": "50.3477", "longitude": "-20.8531"}, "message": "success", "timestamp": 1628016668}, {"iss_position": {"latitude": "50.3402", "longitude": "-20.8059"}, "message": "success", "timestamp": 1628016668}, {"iss_position": {"latitude": "50.3326", "longitude": "-20.7587"}, "message": "success", "timestamp": 1628016669}, {"iss_position": {"latitude": "50.3251", "longitude": "-20.7115"}, "message": "success", "timestamp": 1628016669}, {"iss_position": {"latitude": "50.3175", "longitude": "-20.6643"}, "message": "success", "timestamp": 1628016670}, {"iss_position": {"latitude": "50.3100", "longitude": "-20.6171"}, "message": "success", "timestamp": 1628016670}, {"iss_position": {"latitude": "50.3024", "longitude": "-20.5699"}, "message": "success", "timestamp": 1628016671}, {"iss_position": {"latitude": "50.2947", "longitude": "-20.5227"}, "message": "success", "timestamp": 1628016671}, {"iss_position": {"latitude": "50.2871", "longitude": "-20.4756"}, "message": "success", "timestamp": 1628016672}, {"iss_position": {"latitude": "50.2871", "longitude": "-20.4756"}, "message": "success", "timestamp": 1628016672}, {"iss_position": {"latitude": "50.2794", "longitude": "-20.4285"}, "message": "success", "timestamp": 1628016672}, {"iss_position": {"latitude": "50.2717", "longitude": "-20.3814"}, "message": "success", "timestamp": 1628016673}, {"iss_position": {"latitude": "50.2640", "longitude": "-20.3343"}, "message": "success", "timestamp": 1628016673}, {"iss_position": {"latitude": "50.2563", "longitude": "-20.2872"}, "message": "success", "timestamp": 1628016674}, {"iss_position": {"latitude": "50.2485", "longitude": "-20.2401"}, "message": "success", "timestamp": 1628016674}, {"iss_position": {"latitude": "50.2485", "longitude": "-20.2401"}, "message": "success", "timestamp": 1628016674}, {"iss_position": {"latitude": "50.2408", "longitude": "-20.1931"}, "message": "success", "timestamp": 1628016675}, {"iss_position": {"latitude": "50.2330", "longitude": "-20.1460"}, "message": "success", "timestamp": 1628016675}, {"iss_position": {"latitude": "50.2251", "longitude": "-20.0990"}, "message": "success", "timestamp": 1628016676}, {"iss_position": {"latitude": "50.2173", "longitude": "-20.0520"}, "message": "success", "timestamp": 1628016676}, {"iss_position": {"latitude": "50.2094", "longitude": "-20.0050"}, "message": "success", "timestamp": 1628016677}, {"iss_position": {"latitude": "50.2016", "longitude": "-19.9580"}, "message": "success", "timestamp": 1628016677}, {"iss_position": {"latitude": "50.1937", "longitude": "-19.9110"}, "message": "success", "timestamp": 1628016678}, {"iss_position": {"latitude": "50.1937", "longitude": "-19.9110"}, "message": "success", "timestamp": 1628016678}, {"iss_position": {"latitude": "50.1858", "longitude": "-19.8641"}, "message": "success", "timestamp": 1628016678}, {"iss_position": {"latitude": "50.1778", "longitude": "-19.8171"}, "message": "success", "timestamp": 1628016679}, {"iss_position": {"latitude": "50.1699", "longitude": "-19.7702"}, "message": "success", "timestamp": 1628016679}, {"iss_position": {"latitude": "50.1619", "longitude": "-19.7234"}, "message": "success", "timestamp": 1628016680}]